pyheck-0.1.5.dist-info/METADATA
pyheck-0.1.5.dist-info/WHEEL
pyheck-0.1.5.dist-info/license_files/LICENSE
pyheck.libs/libgcc_s-0d63e1c3.so.1
pyheck/__init__.py
pyheck/__init__.pyi
pyheck/py.typed
pyheck/pyheck.abi3.so
pyheck-0.1.5.dist-info/RECORD
