Metadata-Version: 2.1
Name: pyheck
Version: 0.1.5
Classifier: Programming Language :: Rust
Classifier: Programming Language :: Python :: Implementation :: CPython
License-File: LICENSE
Summary: Python bindings for heck, the Rust case conversion library
Author-email: kevinheavey <kevinheavey123@gmail.com>
Requires-Python: >=3.7
Project-URL: documentation, https://kevinheavey.github.io/pyheck/
Project-URL: repository, https://github.com/kevinheavey/pyheck
Project-URL: changelog, https://github.com/kevinheavey/pyheck/blob/main/CHANGELOG.md
Project-URL: homepage, https://github.com/kevinheavey/pyheck
